gpuhunt/__init__.py
gpuhunt/__main__.py
gpuhunt/version.py
gpuhunt/_internal/__init__.py
gpuhunt/_internal/catalog.py
gpuhunt/_internal/constraints.py
gpuhunt/_internal/default.py
gpuhunt/_internal/models.py
gpuhunt/_internal/storage.py
gpuhunt/_internal/utils.py
gpuhunt/providers/__init__.py
gpuhunt/providers/aws.py
gpuhunt/providers/azure.py
gpuhunt/providers/cloudrift.py
gpuhunt/providers/cudo.py
gpuhunt/providers/digitalocean.py
gpuhunt/providers/gcp.py
gpuhunt/providers/hotaisle.py
gpuhunt/providers/lambdalabs.py
gpuhunt/providers/nebius.py
gpuhunt/providers/oci.py
gpuhunt/providers/runpod.py
gpuhunt/providers/tensordock.py
gpuhunt/providers/vastai.py
gpuhunt/providers/verda.py
gpuhunt/providers/vultr.py
gpuhunt/resources/__init__.py
gpuhunt/scripts/__init__.py
gpuhunt/scripts/catalog_v1/__init__.py
gpuhunt/scripts/catalog_v1/__main__.py
gpuhunt-0.1.16.dist-info/licenses/LICENSE
integrity_tests/__init__.py
integrity_tests/conftest.py
integrity_tests/test_all.py
integrity_tests/test_aws.py
integrity_tests/test_azure.py
integrity_tests/test_cloudrift.py
integrity_tests/test_gcp.py
integrity_tests/test_hotaisle.py
integrity_tests/test_lambdalabs.py
integrity_tests/test_nebius.py
integrity_tests/test_oci.py
integrity_tests/test_runpod.py
integrity_tests/test_vastai.py
integrity_tests/test_verda.py
tests/__init__.py
tests/_internal/__init__.py
tests/_internal/test_catalog.py
tests/_internal/test_constraints.py
tests/_internal/test_models.py
tests/_internal/test_utils.py
tests/providers/__init__.py
tests/providers/test_cudo.py
tests/providers/test_digitalocean.py
tests/providers/test_oci.py
tests/providers/test_providers.py
tests/providers/test_tensordock.py
tests/providers/test_verda.py
tests/providers/test_vultr.py
tests/scripts/__init__.py
tests/scripts/test_catalog_v1.py
gpuhunt-0.1.16.dist-info/METADATA
gpuhunt-0.1.16.dist-info/WHEEL
gpuhunt-0.1.16.dist-info/top_level.txt
gpuhunt-0.1.16.dist-info/RECORD
