Metadata-Version: 2.4
Name: gpuhunt
Version: 0.1.16
Summary: A catalog of GPU pricing for different cloud providers
Author: dstack GmbH
Project-URL: GitHub, https://github.com/dstackai/gpuhunt
Project-URL: Issues, https://github.com/dstackai/gpuhunt/issues
Keywords: gpu,cloud,pricing
Classifier: Programming Language :: Python :: 3
Classifier: License :: OSI Approved :: Mozilla Public License 2.0 (MPL 2.0)
Classifier: Operating System :: OS Independent
Requires-Python: >=3.9
License-File: LICENSE
Requires-Dist: requests
Requires-Dist: typing-extensions
Provides-Extra: aws
Requires-Dist: boto3; extra == "aws"
Provides-Extra: azure
Requires-Dist: azure-mgmt-compute; extra == "azure"
Requires-Dist: azure-identity; extra == "azure"
Provides-Extra: gcp
Requires-Dist: google-cloud-billing; extra == "gcp"
Requires-Dist: google-cloud-compute; extra == "gcp"
Requires-Dist: google-cloud-tpu; extra == "gcp"
Provides-Extra: nebius
Requires-Dist: nebius<0.4,>=0.2.40; extra == "nebius"
Provides-Extra: maybe-nebius
Requires-Dist: nebius<0.4,>=0.2.40; python_version >= "3.10" and extra == "maybe-nebius"
Provides-Extra: oci
Requires-Dist: oci; extra == "oci"
Requires-Dist: pydantic<2.0.0,>=1.10.10; extra == "oci"
Provides-Extra: verda
Requires-Dist: verda; extra == "verda"
Provides-Extra: maybe-verda
Requires-Dist: verda; python_version >= "3.10" and extra == "maybe-verda"
Provides-Extra: all
Requires-Dist: gpuhunt[aws,azure,gcp,maybe_nebius,maybe_verda,oci]; extra == "all"
Provides-Extra: dev
Requires-Dist: pre-commit; extra == "dev"
Requires-Dist: pytest~=7.0; extra == "dev"
Requires-Dist: pytest-mock; extra == "dev"
Requires-Dist: ruff==0.5.3; extra == "dev"
Requires-Dist: requests-mock; extra == "dev"
Dynamic: license-file
